boilerplate/__init__.py
boilerplate/boilerplate.py
recycle-1.0.0.dist-info/entry_points.txt
recycle-1.0.0.dist-info/METADATA
recycle-1.0.0.dist-info/WHEEL
recycle-1.0.0.dist-info/metadata.json
recycle-1.0.0.dist-info/RECORD
recycle-1.0.0.dist-info/DESCRIPTION.rst
recycle-1.0.0.dist-info/top_level.txt
recycle/__init__.py
recycle/recycle.py
