Metadata-Version: 2.0
Name: recycle
Version: 1.0.0
Summary: A utility to help recycle commonly use files and templates.
Home-page: williamg.me/recycle
Author: William Ganucheau
Author-email: UNKNOWN
License: MIT
Keywords: productivity utility
Platform: UNKNOWN
Classifier: Development Status :: 4 - Beta
Classifier: Environment :: Console
Classifier: Intended Audience :: End Users/Desktop
Classifier: Intended Audience :: Developers
Classifier: Natural Language :: English
Classifier: Topic :: Utilities
